nets/mobilenet/__init__.py
nets/mobilenet/conv_blocks.py
nets/mobilenet/mobilenet.py
nets/mobilenet/mobilenet_v2.py
nets/mobilenet/mobilenet_v2_test.py
nets/nasnet/__init__.py
nets/nasnet/nasnet.py
nets/nasnet/nasnet_test.py
nets/nasnet/nasnet_utils.py
nets/nasnet/nasnet_utils_test.py
nets/nasnet/pnasnet.py
nets/nasnet/pnasnet_test.py
object_detection/anchor_generators/__init__.py
object_detection/anchor_generators/flexible_grid_anchor_generator.py
object_detection/anchor_generators/flexible_grid_anchor_generator_test.py
object_detection/anchor_generators/grid_anchor_generator.py
object_detection/anchor_generators/grid_anchor_generator_test.py
object_detection/anchor_generators/multiple_grid_anchor_generator.py
object_detection/anchor_generators/multiple_grid_anchor_generator_test.py
object_detection/anchor_generators/multiscale_grid_anchor_generator.py
object_detection/anchor_generators/multiscale_grid_anchor_generator_test.py
object_detection/box_coders/__init__.py
object_detection/box_coders/faster_rcnn_box_coder.py
object_detection/box_coders/faster_rcnn_box_coder_test.py
object_detection/box_coders/keypoint_box_coder.py
object_detection/box_coders/keypoint_box_coder_test.py
object_detection/box_coders/mean_stddev_box_coder.py
object_detection/box_coders/mean_stddev_box_coder_test.py
object_detection/box_coders/square_box_coder.py
object_detection/box_coders/square_box_coder_test.py
object_detection/builders/__init__.py
object_detection/builders/anchor_generator_builder.py
object_detection/builders/anchor_generator_builder_test.py
object_detection/builders/box_coder_builder.py
object_detection/builders/box_coder_builder_test.py
object_detection/builders/box_predictor_builder.py
object_detection/builders/box_predictor_builder_test.py
object_detection/builders/calibration_builder.py
object_detection/builders/calibration_builder_test.py
object_detection/builders/dataset_builder.py
object_detection/builders/dataset_builder_test.py
PSCMRCET_Tensorflow_object_trainer-1.3.0.dist-info/LICENSE.txt
PSCMRCET_Tensorflow_object_trainer-1.3.0.dist-info/METADATA
PSCMRCET_Tensorflow_object_trainer-1.3.0.dist-info/WHEEL
PSCMRCET_Tensorflow_object_trainer-1.3.0.dist-info/top_level.txt
PSCMRCET_Tensorflow_object_trainer-1.3.0.dist-info/RECORD
